lsd_cli/__init__.py
lsd_cli/cli.py
lsd_cli/lsd.py
lsd_cli/print_utils.py
lsd_cli/shell_cmd.py
lsd_cli/vis.py
lsd_cli-0.1.6.3.dist-info/DESCRIPTION.rst
lsd_cli-0.1.6.3.dist-info/METADATA
lsd_cli-0.1.6.3.dist-info/RECORD
lsd_cli-0.1.6.3.dist-info/WHEEL
lsd_cli-0.1.6.3.dist-info/entry_points.txt
lsd_cli-0.1.6.3.dist-info/metadata.json
lsd_cli-0.1.6.3.dist-info/top_level.txt
