Metadata-Version: 2.0
Name: lsd-cli
Version: 0.1.6.3
Summary: Leapsight Semantic Dataspace Command Line Tool
Home-page: https://github.com/frepond/lsd-cli
Author: Federico Repond
Author-email: federico.repond@leapsight.com
License: BSD
Platform: any
Classifier: Development Status :: 4 - Beta
Classifier: Environment :: Console
Classifier: Intended Audience :: Developers
Classifier: License :: OSI Approved :: BSD License
Classifier: Operating System :: POSIX
Classifier: Operating System :: MacOS
Classifier: Operating System :: Unix
Classifier: Programming Language :: Python
Classifier: Programming Language :: Python :: 2
Classifier: Programming Language :: Python :: 3
Classifier: Topic :: Software Development :: Libraries :: Python Modules
Requires-Dist: click
Requires-Dist: prompt-toolkit
Requires-Dist: pygments
Requires-Dist: requests
Requires-Dist: tabulate
Requires-Dist: ujson
Requires-Dist: xtermcolor
